mojo/xmods/__init__.py
mojo/xmods/aspects.py
mojo/xmods/autoclean.py
mojo/xmods/compression.py
mojo/xmods/eventing/__init__.py
mojo/xmods/eventing/enumerations.py
mojo/xmods/eventing/eventedvariable.py
mojo/xmods/eventing/eventedvariablesink.py
mojo/xmods/extension/__init__.py
mojo/xmods/extension/dynamic.py
mojo/xmods/fspath.py
mojo/xmods/injection/constraints.py
mojo/xmods/injection/constraintscatalog.py
mojo/xmods/injection/coupling/__init__.py
mojo/xmods/injection/coupling/basecoupling.py
mojo/xmods/injection/coupling/integrationcoupling.py
mojo/xmods/injection/coupling/scopecoupling.py
mojo/xmods/injection/coupling/validatorcoupling.py
mojo/xmods/injection/decorators/__init__.py
mojo/xmods/injection/decorators/factory.py
mojo/xmods/injection/decorators/injection.py
mojo/xmods/injection/injectablegroup.py
mojo/xmods/injection/injectableref.py
mojo/xmods/injection/injectionregistry.py
mojo/xmods/injection/integrationsource.py
mojo/xmods/injection/origination.py
mojo/xmods/injection/parameterorigin.py
mojo/xmods/injection/resourcelifespan.py
mojo/xmods/injection/resources.py
mojo/xmods/injection/resourcescope.py
mojo/xmods/injection/resourcesource.py
mojo/xmods/injection/scopesource.py
mojo/xmods/injection/sourcebase.py
mojo/xmods/injection/unknownsource.py
mojo/xmods/injection/validatororigin.py
mojo/xmods/injection/validatorsource.py
mojo/xmods/jsos.py
mojo/xmods/markers.py
mojo/xmods/modeling/__init__.py
mojo/xmods/modeling/extensionproperty.py
mojo/xmods/verification.py
mojo/xmods/wrappers/__init__.py
mojo/xmods/wrappers/fsdict.py
mojo/xmods/xclick.py
mojo/xmods/xconvert.py
mojo/xmods/xdata/__init__.py
mojo/xmods/xdata/datahelpers.py
mojo/xmods/xdata/datamap.py
mojo/xmods/xdata/datanode.py
mojo/xmods/xdata/generators/__init__.py
mojo/xmods/xdata/generators/integerboundarygenerator.py
mojo/xmods/xdata/generators/listgenerator.py
mojo/xmods/xdata/generators/valuegenerator.py
mojo/xmods/xdatetime.py
mojo/xmods/xdebugger.py
mojo/xmods/xfeature.py
mojo_xmodules-2.0.2.dist-info/LICENSE.txt
mojo_xmodules-2.0.2.dist-info/METADATA
mojo_xmodules-2.0.2.dist-info/WHEEL
mojo_xmodules-2.0.2.dist-info/RECORD
